{
  "books": [
    {
      "bookTitle": "The Great Gatsby",
      "authorName": "F. Scott Fitzgerald",
      "genre": "Classic, Fiction",
      "publicationYear": 1925,
      "ISBN": "9780743273565",
      "publisher": "Scribner",
      "language": "English",
      "pageCount": 180,
      "rating": 4.2,
      "price": "$10.99"
    },
    {
      "bookTitle": "1984",
      "authorName": "George Orwell",
      "genre": "Dystopian, Fiction",
      "publicationYear": 1949,
      "ISBN": "9780451524935",
      "publisher": "Secker & Warburg",
      "language": "English",
      "pageCount": 328,
      "rating": 4.3,
      "price": "$9.99"
    },
    {
      "bookTitle": "To Kill a Mockingbird",
      "authorName": "Harper Lee",
      "genre": "Fiction, Drama",
      "publicationYear": 1960,
      "ISBN": "9780061120084",
      "publisher": "J.B. Lippincott & Co.",
      "language": "English",
      "pageCount": 281,
      "rating": 4.5,
      "price": "$8.99"
    },
    {
      "bookTitle": "Pride and Prejudice",
      "authorName": "Jane Austen",
      "genre": "Classic, Romance",
      "publicationYear": 1813,
      "ISBN": "9780141439518",
      "publisher": "T. Egerton",
      "language": "English",
      "pageCount": 279,
      "rating": 4.4,
      "price": "$7.99"
    },
    {
      "bookTitle": "The Catcher in the Rye",
      "authorName": "J.D. Salinger",
      "genre": "Classic, Fiction",
      "publicationYear": 1951,
      "ISBN": "9780316769488",
      "publisher": "Little, Brown and Company",
      "language": "English",
      "pageCount": 277,
      "rating": 4.0,
      "price": "$9.49"
    },
    {
      "bookTitle": "Moby Dick",
      "authorName": "Herman Melville",
      "genre": "Adventure, Classic",
      "publicationYear": 1851,
      "ISBN": "9780142437247",
      "publisher": "Harper & Brothers",
      "language": "English",
      "pageCount": 635,
      "rating": 3.8,
      "price": "$12.99"
    },
    {
      "bookTitle": "The Hobbit",
      "authorName": "J.R.R. Tolkien",
      "genre": "Fantasy, Adventure",
      "publicationYear": 1937,
      "ISBN": "9780547928227",
      "publisher": "George Allen & Unwin",
      "language": "English",
      "pageCount": 310,
      "rating": 4.8,
      "price": "$10.99"
    },
    {
      "bookTitle": "The Odyssey",
      "authorName": "Homer",
      "genre": "Epic Poetry, Classic",
      "publicationYear": -800,
      "ISBN": "9780140268867",
      "publisher": "Penguin Classics",
      "language": "Greek",
      "pageCount": 541,
      "rating": 4.1,
      "price": "$11.99"
    },
    {
      "bookTitle": "War and Peace",
      "authorName": "Leo Tolstoy",
      "genre": "Historical Fiction",
      "publicationYear": 1869,
      "ISBN": "9780307388881",
      "publisher": "The Russian Messenger",
      "language": "Russian",
      "pageCount": 1296,
      "rating": 4.3,
      "price": "$14.99"
    },
    {
      "bookTitle": "Harry Potter and the Sorcerer's Stone",
      "authorName": "J.K. Rowling",
      "genre": "Fantasy, Fiction",
      "publicationYear": 1997,
      "ISBN": "9780439708180",
      "publisher": "Bloomsbury Publishing",
      "language": "English",
      "pageCount": 309,
      "rating": 4.7,
      "price": "$10.99"
    },
    {
      "bookTitle": "The Picture of Dorian Gray",
      "authorName": "Oscar Wilde",
      "genre": "Classic, Gothic",
      "publicationYear": 1890,
      "ISBN": "9780141439570",
      "publisher": "Ward, Lock & Co.",
      "language": "English",
      "pageCount": 254,
      "rating": 4.0,
      "price": "$6.99"
    },
    {
      "bookTitle": "Frankenstein",
      "authorName": "Mary Shelley",
      "genre": "Horror, Gothic Fiction",
      "publicationYear": 1818,
      "ISBN": "9780486282114",
      "publisher": "Lackington, Hughes, Harding, Mavor & Jones",
      "language": "English",
      "pageCount": 280,
      "rating": 4.1,
      "price": "$5.99"
    },
    {
      "bookTitle": "Brave New World",
      "authorName": "Aldous Huxley",
      "genre": "Dystopian, Science Fiction",
      "publicationYear": 1932,
      "ISBN": "9780060850524",
      "publisher": "Chatto & Windus",
      "language": "English",
      "pageCount": 268,
      "rating": 4.2,
      "price": "$8.99"
    },
    {
      "bookTitle": "The Lord of the Rings: The Fellowship of the Ring",
      "authorName": "J.R.R. Tolkien",
      "genre": "Fantasy, Adventure",
      "publicationYear": 1954,
      "ISBN": "9780618574940",
      "publisher": "George Allen & Unwin",
      "language": "English",
      "pageCount": 423,
      "rating": 4.8,
      "price": "$15.99"
    },
    {
      "bookTitle": "The Road",
      "authorName": "Cormac McCarthy",
      "genre": "Post-apocalyptic, Fiction",
      "publicationYear": 2006,
      "ISBN": "9780307387891",
      "publisher": "Alfred A. Knopf",
      "language": "English",
      "pageCount": 287,
      "rating": 4.3,
      "price": "$11.49"
    }
  ]
}
